CHANGELOG.txt
LICENSE.txt
MANIFEST.in
README.md
setup.py
src/geofs/__init__.py
src/geofs/mapAPI.py
src/geofs/multiplayerAPI.py
src/geofs/data/aircraftcodes.json
src/python_geofs.egg-info/PKG-INFO
src/python_geofs.egg-info/SOURCES.txt
src/python_geofs.egg-info/dependency_links.txt
src/python_geofs.egg-info/top_level.txt