Metadata-Version: 2.1
Name: python-geofs
Version: 0.1.5
Summary: An abstraction layer for the GeoFS API
Home-page: https://github.com/iL0g1c/python-geofs
Author: Osprey
License: MIT
License-File: LICENSE.txt
